setup.py
MockBear/MockBear.py
MockBear/__init__.py
MockBearTest.egg-info/PKG-INFO
MockBearTest.egg-info/SOURCES.txt
MockBearTest.egg-info/dependency_links.txt
MockBearTest.egg-info/entry_points.txt
MockBearTest.egg-info/requires.txt
MockBearTest.egg-info/top_level.txt